setup.py
gitfolio/__init__.py
gitfolio/builder.py
gitfolio/ghAuth.py
gitfolio/gitfolio_run.py
gitfolio/summarize_v1.py
gitfolio/summarize_v2.py
gitfolio.egg-info/PKG-INFO
gitfolio.egg-info/SOURCES.txt
gitfolio.egg-info/dependency_links.txt
gitfolio.egg-info/top_level.txt