Metadata-Version: 1.0
Name: gitfolio
Version: 0.9.1
Summary: Gather all your GitHub repositories, and a small descripton of them into one file, and then send it off.
Home-page: https://github.com/CalderWhite/myGitFolio
Author: Calder White
Author-email: calderwhite1@gmail.com
License: UNKNOWN
Platform: UNKNOWN
